LICENSE
README.md
setup.cfg
setup.py
svs_dataset_downloader/__init__.py
svs_dataset_downloader/downloader.py
svs_dataset_downloader.egg-info/PKG-INFO
svs_dataset_downloader.egg-info/SOURCES.txt
svs_dataset_downloader.egg-info/dependency_links.txt
svs_dataset_downloader.egg-info/requires.txt
svs_dataset_downloader.egg-info/top_level.txt