Metadata-Version: 2.1
Name: svs-dataset-downloader
Version: 0.0.2
Summary: Testing installation of Package
Home-page: https://github.com/Manas1820/svs-dataset-downloader
Download-URL: https://github.com/Manas1820/svs-dataset-downloader/archive/refs/tags/v0.0.2.tar.gz
Author: Manas Gupta
Author-email: manasgupta1820@gmail.com
License: MIT
Project-URL: Bug Tracker, https://github.com/Manas1820/svs-dataset-downloader/issues
Keywords: pypi,selenium,medical
Classifier: Development Status :: 3 - Alpha
Classifier: Intended Audience :: Developers
Classifier: Topic :: Software Development :: Documentation
Classifier: License :: OSI Approved :: MIT License
Classifier: Programming Language :: Python :: 3
Classifier: Programming Language :: Python :: 3.7
Classifier: Programming Language :: Python :: 3.8
Classifier: Programming Language :: Python :: 3.9
License-File: LICENSE
